rate_distortion/evaluate.py
rate_distortion-0.0.2.dist-info/licenses/LICENSE
rate_distortion-0.0.2.dist-info/METADATA
rate_distortion-0.0.2.dist-info/WHEEL
rate_distortion-0.0.2.dist-info/top_level.txt
rate_distortion-0.0.2.dist-info/RECORD
