Metadata-Version: 2.4
Name: rate-distortion
Version: 0.0.2
Summary: Rate Distortion
Author-email: Dan Jacobellis <danjacobellis@utexas.edu>
License-Expression: LicenseRef-Proprietary
Classifier: Programming Language :: Python :: 3
Classifier: Operating System :: OS Independent
Requires-Python: >=3.6
License-File: LICENSE
Requires-Dist: torch
Requires-Dist: pillow
Requires-Dist: piq
Dynamic: license-file
